jiboia_gpu/__init__.py
jiboia_gpu/boolean/__init__.py
jiboia_gpu/boolean/boolean_utils.py
jiboia_gpu/boolean/regex_pattern.py
jiboia_gpu/dataframe/__init__.py
jiboia_gpu/dataframe/df_utils.py
jiboia_gpu/datetime/__init__.py
jiboia_gpu/datetime/datetime_utils.py
jiboia_gpu/datetime/regex_pattern.py
jiboia_gpu/null/__init__.py
jiboia_gpu/null/null_utils.py
jiboia_gpu/null/regex_pattern.py
jiboia_gpu/number/__init__.py
jiboia_gpu/number/number_utils.py
jiboia_gpu/number/regex_pattern.py
jiboia_gpu/string/__init__.py
jiboia_gpu/string/string_utils.py
jiboia_gpu/time/__init__.py
jiboia_gpu/time/regex_pattern.py
jiboia_gpu/time/time_utils.py
jiboia_gpu/utils/__init__.py
jiboia_gpu/utils/chunk_utils.py
jiboia_gpu/utils/csv_utils.py
jiboia_gpu/utils/log_utils.py
jiboia_gpu/utils/str_utils.py
jiboia_gpu/utils/validation_utils.py
jiboia_gpu-2.1.0.dist-info/licenses/LICENSE
jiboia_gpu-2.1.0.dist-info/METADATA
jiboia_gpu-2.1.0.dist-info/WHEEL
jiboia_gpu-2.1.0.dist-info/top_level.txt
jiboia_gpu-2.1.0.dist-info/RECORD
