Metadata-Version: 2.4
Name: jiboia-gpu
Version: 2.1.0
Summary: jiboia gpu is a python package for automatically normalizing DataFrames and optimizing types efficiently.
Author-email: Lucas Muffato <lucasmuffato.eng@gmail.com>
License: MIT License
Project-URL: Homepage, https://github.com/lmuffato/jiboia-gpu
Project-URL: Bug_Tracker, https://github.com/lmuffato/jiboia-gpu/issues
Project-URL: LinkedIn, https://www.linkedin.com/in/lucasmuffato/
Requires-Python: >=3.9
License-File: LICENSE
Requires-Dist: cudf-cu12>=25.8
Provides-Extra: dev
Requires-Dist: pytest>=7.0; extra == "dev"
Requires-Dist: pytest-cov>=4.0; extra == "dev"
Dynamic: license-file
